Workbook

Sheet 前提
A1: 夢プロ 初回実証（ホテル1施設・1商品・90日）採算モデル ― 前提条件
A2: すべて仮定の数字です（実績・見積・売上予測ではありません）。青字=入力値、黄色=特に未確定で影響が大きい値。金額は税抜・円。
A4: アチーバーの収入（施設・スポンサーから受領）
A5: 企画運営費（初期一括） | B5: 800000 | C5: 仮定。商品設計・撮影段取り・紹介ページ・予約連携設計まで
A6: 月額運営料（1か月） | B6: 250000 | C6: 仮定。発信運用・問い合わせ補助・週次集計・月次報告
A7: 運営月数 | B7: 3 | C7: 初回実証期間
A8: 個別案件費 件数 | B8: 0 | C8: 追加動画・季節差し替え等。基本ケースは0件
A9: 個別案件費 単価 | B9: 150000 | C9: 仮定
A10: 協賛 社数 | B10: 0 | C10: 基本ケースは0社（未獲得のため）。シナリオシートで1〜2社を試算
A11: 協賛 単価（1社） | B11: 500000 | C11: 仮定。協賛商品「体験提供＋動画内紹介＋ページ掲載」
A12: 協賛履行の追加原価（1社） | B12: 50000 | C12: 紹介カット追加撮影・編集など
A14: アチーバーの外部支出（キャッシュアウト）
A15: 出演費（体験出演・発信 一式） | B15: 400000 | C15: 仮定。鈴木優香さんの参加・金額・投稿条件は未確定
A16: 撮影費（外部撮影 1日） | B16: 200000 | C16: 仮定
A17: 編集外注費 | B17: 150000 | C17: 仮定。短尺動画の仕上げ。AIチームは下書き・切り出し補助
A18: 交通費 | B18: 50000 | C18: 仮定。施設の所在地で大きく変動
A19: 広告費（90日合計） | B19: 300000 | C19: 仮定。SNS広告の配信費
A20: 広告費の扱い（1=施設が実費負担 / 0=アチーバー負担） | B20: 0 | C20: 基本ケースはアチーバー負担（保守的）
A21: システム費（月額） | B21: 30000 | C21: 紹介ページ・計測ツール・ドメイン等
A22: AIツール利用料（月額） | B22: 20000 | C22: 仮定
A23: 個別案件 1件あたり外部原価 | B23: 50000 | C23: 仮定
A25: 社内作業費（工数×単価。キャッシュではなく機会費用として計上）
A26: 人の作業時間（営業・提案・契約調整・進行・確認） | B26: 60 | C26: 時間。選考・交渉・公開確認・契約判断は人が行う
A27: 人の時間単価 | B27: 8000 | C27: 仮定
A28: AIチーム作業時間（人による確認・修正を含む） | B28: 50 | C28: 時間。AIチームの処理能力は未実証のため、時間短縮を見込まず計上
A29: AIチーム時間単価 | B29: 5000 | C29: 仮定
A30: 個別案件 1件あたり人の作業時間 | B30: 8 | C30: 時間
A32: 施設側（ホテル）
A33: プラン販売価格（1室2名・税抜） | B33: 80000 | C33: 仮定。宿泊＋夕朝食＋スパ
A34: うち客室 | B34: 40000 | C34: 仮定
A35: うち食事 | B35: 24000 | C35: 仮定
A36: うちスパ | B36: 16000 | C36: 仮定
A37: 客室変動費（1室：清掃・リネン・アメニティ） | B37: 6000 | C37: 仮定
A38: 食事原価率 | B38: 0.32 | C38: 仮定
A39: スパ原価率（施設→クレドへの施術料の比率） | B39: 0.6 | C39: 仮定。クレドと施設の契約形態は未確定
A40: 識別できた予約完了数（90日） | B40: 20 | C40: 仮定の入力値。予測ではない。専用プランコードで識別できた件数
A41: キャンセル率 | B41: 0.1 | C41: 仮定
A42: 増分率（この施策がなければ発生しなかった予約の割合） | B42: 0.7 | C42: 仮定。既存客の振替を差し引くための係数
A43: 施設の撮影協力原価（撮影時の宿泊・食事・スパ提供） | B43: 60000 | C43: 仮定。施設の原価ベース
A44: 内訳チェック（客室＋食事＋スパ − 販売価格。0であること） | B44: =B34+B35+B36-B33 -> 0

Sheet アチーバー案件収支
A1: アチーバー側 案件収支（初回90日）
A2: 仮定の数字による試算。施設の売上・利益とは別勘定。総売上を利益や分配原資として扱わない。
A4: 収入
A5: 企画運営費 | B5: =前提!B5 -> 800000 | C5: 施設から
A6: 月額運営料 | B6: =前提!B6*前提!B7 -> 750000 | C6: 施設から
A7: 個別案件費 | B7: =前提!B8*前提!B9 -> 0 | C7: 施設から
A8: 協賛売上 | B8: =前提!B10*前提!B11 -> 0 | C8: スポンサーから
A9: 広告費の実費請求 | B9: =IF(前提!B20=1,前提!B19,0) -> 0 | C9: 施設負担の場合のみ（同額を支出にも計上）
A10: 収入合計 | B10: =SUM(B5:B9) -> 1550000
A12: 外部支出
A13: 出演費 | B13: =前提!B15 -> 400000
A14: 撮影費 | B14: =前提!B16 -> 200000
A15: 編集外注費 | B15: =前提!B17 -> 150000
A16: 交通費 | B16: =前提!B18 -> 50000
A17: 広告費 | B17: =前提!B19 -> 300000
A18: システム費 | B18: =前提!B21*前提!B7 -> 90000
A19: AIツール利用料 | B19: =前提!B22*前提!B7 -> 60000
A20: 協賛履行の追加原価 | B20: =前提!B10*前提!B12 -> 0
A21: 個別案件の外部原価 | B21: =前提!B8*前提!B23 -> 0
A22: 外部支出合計 | B22: =SUM(B13:B21) -> 1250000
A23: 現金ベースの粗利（収入−外部支出） | B23: =B10-B22 -> 300000 | C23: キャッシュが残るかの判定
A25: 社内作業費
A26: 人の作業費 | B26: =前提!B26*前提!B27+前提!B8*前提!B30*前提!B27 -> 480000 | C26: 基本工数＋個別案件分
A27: AIチーム作業費 | B27: =前提!B28*前提!B29 -> 250000
A28: 作業費合計 | B28: =B26+B27 -> 730000
A30: 案件利益（工数込み） | B30: =B23-B28 -> -430000 | C30: 継続判断に使う利益
A31: 案件利益率 | B31: =IF(B10=0,0,B30/B10) -> -0.27741935
A32: 協賛1社あたりの利益寄与 | B32: =前提!B11-前提!B12 -> 450000
A33: 工数込み黒字に必要な協賛社数 | B33: =IF(B30>=0,0,ROUNDUP(-B30/B32,0)) -> 1 | C33: 協賛以外の条件は現状のまま

Sheet 施設収支
A1: 施設側 収支（初回90日・本プラン分のみ）
A2: 仮定の数字による試算。予約数は入力値であり予測ではない。売上は利用完了ベース。
A4: 件数
A5: 識別できた予約完了 | B5: =前提!B40 -> 20 | C5: 専用プランコードで識別。識別できない予約は含めない
A6: キャンセル | B6: =ROUND(前提!B40*前提!B41,0) -> 2
A7: 利用完了 | B7: =B5-B6 -> 18 | C7: チェックアウト済み
A9: 売上・変動費（利用完了ベース）
A10: プラン売上 | B10: =B7*前提!B33 -> 1440000
A11: 客室変動費 | B11: =B7*前提!B37 -> 108000
A12: 食事原価 | B12: =B7*前提!B35*前提!B38 -> 138240
A13: スパ原価（クレドへの施術料） | B13: =B7*前提!B36*前提!B39 -> 172800
A14: 限界利益 | B14: =B10-B11-B12-B13 -> 1020960
A15: 1室あたり限界利益 | B15: =IF(B7=0,0,B14/B7) -> 56720
A16: 増分限界利益（×増分率） | B16: =B14*前提!B42 -> 714672 | C16: 既存客の振替分を除外
A18: 施策の費用
A19: アチーバーへの支払（企画運営費＋月額＋個別＋広告実費） | B19: =アチーバー案件収支!B5+アチーバー案件収支!B6+アチーバー案件収支!B7+アチーバー案件収支!B9 -> 1550000 | C19: 協賛金はスポンサーが支払うため含まない
A20: 撮影協力原価 | B20: =前提!B43 -> 60000
A21: 施策費用合計 | B21: =B19+B20 -> 1610000
A23: 施設の増分利益（90日） | B23: =B16-B21 -> -895328 | C23: 継続判断に使う利益
A24: 損益分岐に必要な利用完了数 | B24: =IF(B15*前提!B42=0,0,ROUNDUP(B21/((前提!B33-前提!B37-前提!B35*前提!B38-前提!B36*前提!B39)*前提!B42),0)) -> 41 | C24: 1室限界利益×増分率で施策費用を回収する件数
A25: 損益分岐に必要な予約完了数（キャンセル考慮） | B25: =IF(前提!B41>=1,0,ROUNDUP(B24/(1-前提!B41),0)) -> 46
A27: 参考：クレド側
A28: スパ施術料（施設→クレド） | B28: =B13 -> 172800 | C28: 契約形態（施術料・場所代・売上分配）は未確定。クレドの利益はここから施術者人件費等を引いたもの

Sheet シナリオ
A1: 感応度（仮定の数字による試算。予測ではない）
A3: 表1 アチーバー案件利益（工数込み）× 協賛社数
A4: 協賛社数 | B4: 0 | C4: 1 | D4: 2 | E4: 3
A5: 案件利益 | B5: =アチーバー案件収支!$B$30-前提!$B$10*アチーバー案件収支!$B$32+B4*アチーバー案件収支!$B$32 -> -430000 | C5: =アチーバー案件収支!$B$30-前提!$B$10*アチーバー案件収支!$B$32+C4*アチーバー案件収支!$B$32 -> 20000 | D5: =アチーバー案件収支!$B$30-前提!$B$10*アチーバー案件収支!$B$32+D4*アチーバー案件収支!$B$32 -> 470000 | E5: =アチーバー案件収支!$B$30-前提!$B$10*アチーバー案件収支!$B$32+E4*アチーバー案件収支!$B$32 -> 920000
A7: 表2 施設の増分利益（90日）× 識別できた予約完了数
A8: 予約完了数 | B8: 10 | C8: 20 | D8: 40 | E8: 60
A9: 施設の増分利益 | B9: =(B8-ROUND(B8*前提!$B$41,0))*(前提!$B$33-前提!$B$37-前提!$B$35*前提!$B$38-前提!$B$36*前提!$B$39)*前提!$B$42-施設収支!$B$21 -> -1252664 | C9: =(C8-ROUND(C8*前提!$B$41,0))*(前提!$B$33-前提!$B$37-前提!$B$35*前提!$B$38-前提!$B$36*前提!$B$39)*前提!$B$42-施設収支!$B$21 -> -895328 | D9: =(D8-ROUND(D8*前提!$B$41,0))*(前提!$B$33-前提!$B$37-前提!$B$35*前提!$B$38-前提!$B$36*前提!$B$39)*前提!$B$42-施設収支!$B$21 -> -180656 | E9: =(E8-ROUND(E8*前提!$B$41,0))*(前提!$B$33-前提!$B$37-前提!$B$35*前提!$B$38-前提!$B$36*前提!$B$39)*前提!$B$42-施設収支!$B$21 -> 534016
A11: 読み方：表1は協賛以外を前提シートのまま、表2は予約数以外を前提シートのままにした試算。
A12: 現在の仮定では、施設が損益分岐に達するのに必要な件数と、アチーバーが工数込みで黒字化する条件が両立しにくい。料金設計の論点として使う。

Sheet 先行負担
A1: アチーバーの先行負担（施設と契約・着手金入金前）
A2: 原則：契約前は外部への発注をしない。出演費・撮影費・広告費は契約と着手金入金の後に発注。
A4: 項目 | B4: 時間 | C4: 単価 | D4: 金額 | E4: 備考
A5: 施設調査・提案書作成（AIチーム） | B5: 12 | C5: =前提!B29 -> 5000 | D5: =B5*C5 -> 60000 | E5: 確認・修正時間を含む
A6: 提案・打合せ・出演打診の準備（人） | B6: 15 | C6: =前提!B27 -> 8000 | D6: =B6*C6 -> 120000 | E6: 白井さん同席の打合せ含む
A7: デモ・紹介ページ試作（AIチーム） | B7: 8 | C7: =前提!B29 -> 5000 | D7: =B7*C7 -> 40000 | E7: 公開しない試作
A8: 交通費（現地確認） | D8: 20000 | E8: 実費
A10: 先行負担 合計（工数込み） | D10: =SUM(D5:D8) -> 240000
A11: うち外部支出 | D11: =D8 -> 20000
A13: 上限（工数込み） | D13: 300000 | E13: 仮定。超える場合は斎藤が継続可否を判断
A14: 上限（外部支出） | D14: 100000
A16: 判定 | D16: =IF(AND(D10<=D13,D11<=D14),"上限内","斎藤の判断が必要") -> 上限内
A18: 上限の考え方
A19: 1. 契約前に失ってよい金額を先に決める。今回は「工数込み30万円・外部支出10万円」を仮置き。
A20: 2. 出演費・撮影費・広告費は、施設との契約締結と着手金（企画運営費の50%を想定）の入金後に発注する。
A21: 3. 出演者への正式依頼は、出演条件・肖像利用範囲・費用負担者が決まってから行う。
A22: 4. 施設の合意が得られない場合、作成済みの調査・提案書は次の施設候補に転用する。

Sheet 共同余剰分析
A1: 共同余剰分析（施設＋アチーバーの合計。料金の取り合いでは変わらない部分）
A2: 仮定の数字による試算。予測ではない。クレドのスパ利益は原価不明のため含めない。
A4: 施設の増分利益 | B4: =施設収支!B23 -> -895328
A5: アチーバーの案件利益（工数込み） | B5: =アチーバー案件収支!B30 -> -430000
A6: 合計余剰 | B6: =B4+B5 -> -1325328
A7: 検算：利用完了×1室増分限界利益＋協賛純額−固定費 | B7: =施設収支!B7*施設収支!B15*前提!B42+前提!B10*アチーバー案件収支!B32-B9 -> -1325328
A8: 1室あたり増分限界利益（限界利益×増分率） | B8: =(前提!B33-前提!B37-前提!B35*前提!B38-前提!B36*前提!B39)*前提!B42 -> 39704
A9: 初回の固定費合計（外部支出＋作業費＋撮影協力。協賛・個別・広告実費請求を除く） | B9: =前提!B15+前提!B16+前提!B17+前提!B18+前提!B19+(前提!B21+前提!B22)*前提!B7+アチーバー案件収支!B28-前提!B8*前提!B30*前提!B27+前提!B43 -> 2040000
A11: 表A 合計で黒字になる件数（協賛社数別）
A12: 協賛社数 | B12: 必要な利用完了数 | C12: 必要な予約完了数
A13: 0 | B13: =MAX(0,ROUNDUP(($B$9-A13*アチーバー案件収支!$B$32)/$B$8,0)) -> 52 | C13: =IF(前提!$B$41>=1,0,ROUNDUP(B13/(1-前提!$B$41),0)) -> 58
A14: 1 | B14: =MAX(0,ROUNDUP(($B$9-A14*アチーバー案件収支!$B$32)/$B$8,0)) -> 41 | C14: =IF(前提!$B$41>=1,0,ROUNDUP(B14/(1-前提!$B$41),0)) -> 46
A15: 2 | B15: =MAX(0,ROUNDUP(($B$9-A15*アチーバー案件収支!$B$32)/$B$8,0)) -> 29 | C15: =IF(前提!$B$41>=1,0,ROUNDUP(B15/(1-前提!$B$41),0)) -> 33
A16: 3 | B16: =MAX(0,ROUNDUP(($B$9-A16*アチーバー案件収支!$B$32)/$B$8,0)) -> 18 | C16: =IF(前提!$B$41>=1,0,ROUNDUP(B16/(1-前提!$B$41),0)) -> 20
A18: 表B 1施設あたり固定費を下げた場合の必要件数（協賛なし）
A19: 1施設あたり固定費 | B19: 必要な利用完了数 | C19: 必要な予約完了数
A20: 2040000 | B20: =ROUNDUP(A20/$B$8,0) -> 52 | C20: =IF(前提!$B$41>=1,0,ROUNDUP(B20/(1-前提!$B$41),0)) -> 58
A21: 1500000 | B21: =ROUNDUP(A21/$B$8,0) -> 38 | C21: =IF(前提!$B$41>=1,0,ROUNDUP(B21/(1-前提!$B$41),0)) -> 43
A22: 1000000 | B22: =ROUNDUP(A22/$B$8,0) -> 26 | C22: =IF(前提!$B$41>=1,0,ROUNDUP(B22/(1-前提!$B$41),0)) -> 29
A23: 700000 | B23: =ROUNDUP(A23/$B$8,0) -> 18 | C23: =IF(前提!$B$41>=1,0,ROUNDUP(B23/(1-前提!$B$41),0)) -> 20
A25: 読み方：合計余剰がマイナスのとき、料金をどう分けてもどちらかが赤字になる。改善できるのは件数・増分率・単価・協賛・固定費のいずれか。
